edelweiss/__init__.py
edelweiss/classifier.py
edelweiss/clf_diagnostics.py
edelweiss/clf_utils.py
edelweiss/compatibility_utils.py
edelweiss/custom_clfs.py
edelweiss/custom_regs.py
edelweiss/emulator.py
edelweiss/nflow.py
edelweiss/nflow_utils.py
edelweiss/reg_utils.py
edelweiss/regressor.py
edelweiss/tf_utils.py
edelweiss-0.2.0.dist-info/licenses/AUTHORS.rst
edelweiss-0.2.0.dist-info/licenses/LICENSE
edelweiss-0.2.0.dist-info/METADATA
edelweiss-0.2.0.dist-info/WHEEL
edelweiss-0.2.0.dist-info/top_level.txt
edelweiss-0.2.0.dist-info/RECORD
