Metadata-Version: 2.4
Name: edelweiss
Version: 0.2.0
Summary: emulator for various applications
Author-email: Silvan Fischbacher <silvanf@phys.ethz.ch>
License: MIT License
Project-URL: Source, https://cosmo-docs.phys.ethz.ch/edelweiss
Classifier: Intended Audience :: Science/Research
Classifier: Intended Audience :: Developers
Classifier: License :: OSI Approved :: MIT License
Classifier: Natural Language :: English
Classifier: Programming Language :: Python :: 3
Classifier: Programming Language :: Python :: 3.9
Classifier: Programming Language :: Python :: 3.10
Classifier: Programming Language :: Python :: 3.11
Classifier: Programming Language :: Python :: 3.12
Classifier: Operating System :: OS Independent
Requires-Python: >=3.9
License-File: LICENSE
License-File: AUTHORS.rst
Requires-Dist: catboost
Requires-Dist: cosmic_toolbox>=0.4.2
Requires-Dist: esub-epipe>=1.11.1
Requires-Dist: h5py
Requires-Dist: lightgbm
Requires-Dist: matplotlib
Requires-Dist: numpy
Requires-Dist: pandas
Requires-Dist: packaging
Requires-Dist: pzflow
Requires-Dist: scikit-learn
Requires-Dist: tensorflow>=2.15.0; python_version >= "3.12"
Requires-Dist: tensorflow>=2.10.0; python_version < "3.12"
Requires-Dist: trianglechain
Requires-Dist: xgboost
Dynamic: license-file
